README.rst
setup.py
src/infi/__init__.py
src/infi.dtypes.wwn.egg-info/PKG-INFO
src/infi.dtypes.wwn.egg-info/SOURCES.txt
src/infi.dtypes.wwn.egg-info/dependency_links.txt
src/infi.dtypes.wwn.egg-info/entry_points.txt
src/infi.dtypes.wwn.egg-info/namespace_packages.txt
src/infi.dtypes.wwn.egg-info/not-zip-safe
src/infi.dtypes.wwn.egg-info/requires.txt
src/infi.dtypes.wwn.egg-info/top_level.txt
src/infi/dtypes/__init__.py
src/infi/dtypes/wwn/__init__.py
src/infi/dtypes/wwn/__version__.py