Metadata-Version: 1.1
Name: infi.dtypes.wwn
Version: 0.1
Summary: Datatype for WWN
Home-page: https://github.com/Infinidat/infi.dtypes.wwn
Author: Guy Rozendorn
Author-email: guy@rzn.co.il
License: PSF
Platform: UNKNOWN
Classifier: Intended Audience :: Developers
Classifier: Intended Audience :: System Administrators
Classifier: License :: OSI Approved :: Python Software Foundation License
Classifier: Operating System :: OS Independent
Classifier: Programming Language :: Python
Classifier: Topic :: Software Development :: Libraries :: Python Modules
